cshelve/__init__.py
cshelve/_aws_s3.py
cshelve/_azure_blob_storage.py
cshelve/_cloud_shelf.py
cshelve/_compression.py
cshelve/_config.py
cshelve/_data_processing.py
cshelve/_database.py
cshelve/_encryption.py
cshelve/_factory.py
cshelve/_filesystem.py
cshelve/_flag.py
cshelve/_in_memory.py
cshelve/_parser.py
cshelve/_sftp.py
cshelve/exceptions.py
cshelve/provider_interface.py
cshelve-1.6.0.dist-info/METADATA
cshelve-1.6.0.dist-info/WHEEL
cshelve-1.6.0.dist-info/licenses/LICENSE
cshelve-1.6.0.dist-info/RECORD
