Metadata-Version: 2.4
Name: cshelve
Version: 1.6.0
Summary: Propulsing the shelve module to the cloud
Project-URL: repository, https://github.com/Standard-Cloud/cshelve
Project-URL: homepage, https://github.com/Standard-Cloud/cshelve
Project-URL: documentation, https://standard-cloud.github.io/cshelve/
License-File: LICENSE
Keywords: S3,aws,azure,azure-storage-account,cloud,database,sftp,shelve
Requires-Python: >=3.9
Provides-Extra: aws-s3
Requires-Dist: boto3>=1.36; extra == 'aws-s3'
Provides-Extra: azure-blob
Requires-Dist: azure-identity>=1.19.0; extra == 'azure-blob'
Requires-Dist: azure-storage-blob>=12.23.1; extra == 'azure-blob'
Provides-Extra: encryption
Requires-Dist: pycryptodome>=3.21.0; extra == 'encryption'
Provides-Extra: sftp
Requires-Dist: paramiko>=3.5.1; extra == 'sftp'
